LICENSE
MANIFEST.in
README.md
requirements.txt
setup.cfg
setup.py
ua2nx/__init__.py
ua2nx/ua2nx.py
ua2nx.egg-info/PKG-INFO
ua2nx.egg-info/SOURCES.txt
ua2nx.egg-info/dependency_links.txt
ua2nx.egg-info/requires.txt
ua2nx.egg-info/top_level.txt