Metadata-Version: 1.1
Name: ua2nx
Version: 0.0.4
Summary: Converts UrbanAccess graph into NetworkX MultiDiGraph
Home-page: https://github.com/htenkanen/ua2nx
Author: Henrikki Tenkanen
Author-email: henrikki@mapple.fi
License: MIT
Download-URL: https://github.com/htenkanen/ua2nx/archive/v_04.tar.gz
Platform: any
Classifier: Development Status :: 3 - Alpha
Classifier: Intended Audience :: Developers
Classifier: Topic :: Software Development :: Build Tools
Classifier: License :: OSI Approved :: MIT License
Classifier: Programming Language :: Python :: 3
Classifier: Programming Language :: Python :: 3.6
